tum_gdpr_folder_scanner/__init__.py
tum_gdpr_folder_scanner/folder_scanner.py
tum_gdpr_folder_scanner/main.py
tum_gdpr_folder_scanner-0.1.7.dist-info/entry_points.txt
tum_gdpr_folder_scanner-0.1.7.dist-info/LICENSE
tum_gdpr_folder_scanner-0.1.7.dist-info/WHEEL
tum_gdpr_folder_scanner-0.1.7.dist-info/METADATA
tum_gdpr_folder_scanner-0.1.7.dist-info/RECORD
