Metadata-Version: 2.1
Name: tum-gdpr-folder-scanner
Version: 0.1.7
Summary: Script to check local folders for GDPR-relevant information in the TUM context.
Home-page: https://github.com/pstoeckle/TUM-GDPR-Folder-Scanner.git
License: Apache-2.0
Author: Patrick Stöckle
Author-email: patrick.stoeckle@posteo.de
Maintainer: Patrick Stöckle
Maintainer-email: patrick.stoeckle@posteo.de
Requires-Python: >=3.7,<4.0
Classifier: License :: OSI Approved :: Apache Software License
Classifier: Programming Language :: Python :: 3
Classifier: Programming Language :: Python :: 3.7
Classifier: Programming Language :: Python :: 3.8
Classifier: Programming Language :: Python :: 3.9
Classifier: Programming Language :: Python :: 3.10
Requires-Dist: openpyxl (>=3.0.10,<4.0.0)
Requires-Dist: tika (>=1.24,<2.0)
Requires-Dist: tqdm (>=4.64.1,<5.0.0)
Requires-Dist: typer (>=0.7.0,<0.8.0)
Project-URL: Repository, https://github.com/pstoeckle/TUM-GDPR-Folder-Scanner.git
